{
  "format_version": "1.10.0",
  "minecraft:client_entity": {
    "description": {
      "identifier": "tcsmp:cannon",
      "materials": {
        "default": "entity_alphatest"
      },
      "textures": {
        "default": "textures/entity/cannon"
      },
      "geometry": {
        "default": "geometry.cannon"
      },
      "animations": {
        "root": "animation.cannon.root"
      },
      "scripts": {
        "animate": ["root"],
        "should_update_bones_and_effects_offscreen": true
      },
      "render_controllers": [
        "controller.render.default"
      ]
    }
  }
}
